<profile>

<RTLDesignHierarchy>
<TopModule>
<ModuleName>accelerator</ModuleName>
<InstancesList>
<Instance>
<InstName>grp_accelerator_Pipeline_VITIS_LOOP_47_1_fu_274</InstName>
<ModuleName>accelerator_Pipeline_VITIS_LOOP_47_1</ModuleName>
<IsCompInst>true</IsCompInst>
<ID>274</ID>
</Instance>
<Instance>
<InstName>grp_accelerator_Pipeline_VITIS_LOOP_65_3_fu_298</InstName>
<ModuleName>accelerator_Pipeline_VITIS_LOOP_65_3</ModuleName>
<IsCompInst>true</IsCompInst>
<ID>298</ID>
<InstancesList>
<Instance>
<InstName>grp_model_array_fu_596</InstName>
<ModuleName>model_array</ModuleName>
<IsCompInst>true</IsCompInst>
<ID>596</ID>
</Instance>
</InstancesList>
</Instance>
<Instance>
<InstName>grp_accelerator_Pipeline_VITIS_LOOP_157_9_fu_349</InstName>
<ModuleName>accelerator_Pipeline_VITIS_LOOP_157_9</ModuleName>
<IsCompInst>true</IsCompInst>
<ID>349</ID>
</Instance>
</InstancesList>
</TopModule>
</RTLDesignHierarchy>

<ModuleInformation>
<Module>
<Name>accelerator_Pipeline_VITIS_LOOP_47_1</Name>
<Loops>
<VITIS_LOOP_47_1></VITIS_LOOP_47_1>
</Loops>
<PerformanceEstimates>
<SummaryOfTimingAnalysis>
<TargetClockPeriod>30.30</TargetClockPeriod>
<ClockUncertainty>6.00</ClockUncertainty>
<EstimatedClockPeriod>1.699</EstimatedClockPeriod>
</SummaryOfTimingAnalysis>
<SummaryOfOverallLatency>
<Best-caseLatency>4</Best-caseLatency>
<Average-caseLatency>4</Average-caseLatency>
<Worst-caseLatency>4</Worst-caseLatency>
<Best-caseRealTimeLatency>0.121 us</Best-caseRealTimeLatency>
<Average-caseRealTimeLatency>0.121 us</Average-caseRealTimeLatency>
<Worst-caseRealTimeLatency>0.121 us</Worst-caseRealTimeLatency>
<PipelineInitiationInterval>3</PipelineInitiationInterval>
<PipelineType>loop auto-rewind (delay=0 clock cycles(s))</PipelineType>
</SummaryOfOverallLatency>
<SummaryOfLoopLatency>
<VITIS_LOOP_47_1>
<Name>VITIS_LOOP_47_1</Name>
<Slack>24.30</Slack>
<TripCount>2</TripCount>
<Latency>2</Latency>
<AbsoluteTimeLatency>60.606 ns</AbsoluteTimeLatency>
<PipelineII>1</PipelineII>
<PipelineDepth>2</PipelineDepth>
<PipelineType>yes</PipelineType>
<InstanceList>
</InstanceList>
</VITIS_LOOP_47_1>
</SummaryOfLoopLatency>
<SummaryOfViolations>
<IssueType>-</IssueType>
<ViolationType>-</ViolationType>
<SourceLocation>../accelerator.cpp:47</SourceLocation>
<SummaryOfLoopViolations>
<VITIS_LOOP_47_1>
<Name>VITIS_LOOP_47_1</Name>
<IssueType>-</IssueType>
<ViolationType>-</ViolationType>
<SourceLocation>../accelerator.cpp:51</SourceLocation>
</VITIS_LOOP_47_1>
</SummaryOfLoopViolations>
</SummaryOfViolations>
</PerformanceEstimates>
<AreaEstimates>
<Resources>
<FF>198</FF>
<AVAIL_FF>141120</AVAIL_FF>
<UTIL_FF>~0</UTIL_FF>
<LUT>366</LUT>
<AVAIL_LUT>70560</AVAIL_LUT>
<UTIL_LUT>~0</UTIL_LUT>
<BRAM_18K>0</BRAM_18K>
<AVAIL_BRAM>432</AVAIL_BRAM>
<UTIL_BRAM>0</UTIL_BRAM>
<DSP>0</DSP>
<AVAIL_DSP>360</AVAIL_DSP>
<UTIL_DSP>0</UTIL_DSP>
<URAM>0</URAM>
<AVAIL_URAM>0</AVAIL_URAM>
<UTIL_URAM>0</UTIL_URAM>
</Resources>
</AreaEstimates>
<InterfaceSummary>
<RtlPorts>
<name>ap_clk</name>
<Object>accelerator_Pipeline_VITIS_LOOP_47_1</Object>
<Type>return value</Type>
<Scope></Scope>
<IOProtocol>ap_ctrl_hs</IOProtocol>
<IOConfig></IOConfig>
<Dir>in</Dir>
<Bits>1</Bits>
<Attribute>control</Attribute>
</RtlPorts>
<RtlPorts>
<name>ap_rst</name>
<Object>accelerator_Pipeline_VITIS_LOOP_47_1</Object>
<Type>return value</Type>
<Scope></Scope>
<IOProtocol>ap_ctrl_hs</IOProtocol>
<IOConfig></IOConfig>
<Dir>in</Dir>
<Bits>1</Bits>
<Attribute>control</Attribute>
</RtlPorts>
<RtlPorts>
<name>ap_start</name>
<Object>accelerator_Pipeline_VITIS_LOOP_47_1</Object>
<Type>return value</Type>
<Scope></Scope>
<IOProtocol>ap_ctrl_hs</IOProtocol>
<IOConfig></IOConfig>
<Dir>in</Dir>
<Bits>1</Bits>
<Attribute>control</Attribute>
</RtlPorts>
<RtlPorts>
<name>ap_done</name>
<Object>accelerator_Pipeline_VITIS_LOOP_47_1</Object>
<Type>return value</Type>
<Scope></Scope>
<IOProtocol>ap_ctrl_hs</IOProtocol>
<IOConfig></IOConfig>
<Dir>out</Dir>
<Bits>1</Bits>
<Attribute>control</Attribute>
</RtlPorts>
<RtlPorts>
<name>ap_idle</name>
<Object>accelerator_Pipeline_VITIS_LOOP_47_1</Object>
<Type>return value</Type>
<Scope></Scope>
<IOProtocol>ap_ctrl_hs</IOProtocol>
<IOConfig></IOConfig>
<Dir>out</Dir>
<Bits>1</Bits>
<Attribute>control</Attribute>
</RtlPorts>
<RtlPorts>
<name>ap_ready</name>
<Object>accelerator_Pipeline_VITIS_LOOP_47_1</Object>
<Type>return value</Type>
<Scope></Scope>
<IOProtocol>ap_ctrl_hs</IOProtocol>
<IOConfig></IOConfig>
<Dir>out</Dir>
<Bits>1</Bits>
<Attribute>control</Attribute>
</RtlPorts>
<RtlPorts>
<name>w1_address0</name>
<Object>w1</Object>
<Type>array</Type>
<Scope></Scope>
<IOProtocol>ap_memory</IOProtocol>
<IOConfig></IOConfig>
<Dir>out</Dir>
<Bits>2</Bits>
<Attribute>address</Attribute>
</RtlPorts>
<RtlPorts>
<name>w1_ce0</name>
<Object>w1</Object>
<Type>array</Type>
<Scope></Scope>
<IOProtocol>ap_memory</IOProtocol>
<IOConfig></IOConfig>
<Dir>out</Dir>
<Bits>1</Bits>
<Attribute>control</Attribute>
</RtlPorts>
<RtlPorts>
<name>w1_q0</name>
<Object>w1</Object>
<Type>array</Type>
<Scope></Scope>
<IOProtocol>ap_memory</IOProtocol>
<IOConfig></IOConfig>
<Dir>in</Dir>
<Bits>16</Bits>
<Attribute>data</Attribute>
</RtlPorts>
<RtlPorts>
<name>w1_address1</name>
<Object>w1</Object>
<Type>array</Type>
<Scope></Scope>
<IOProtocol>ap_memory</IOProtocol>
<IOConfig></IOConfig>
<Dir>out</Dir>
<Bits>2</Bits>
<Attribute>address</Attribute>
</RtlPorts>
<RtlPorts>
<name>w1_ce1</name>
<Object>w1</Object>
<Type>array</Type>
<Scope></Scope>
<IOProtocol>ap_memory</IOProtocol>
<IOConfig></IOConfig>
<Dir>out</Dir>
<Bits>1</Bits>
<Attribute>control</Attribute>
</RtlPorts>
<RtlPorts>
<name>w1_q1</name>
<Object>w1</Object>
<Type>array</Type>
<Scope></Scope>
<IOProtocol>ap_memory</IOProtocol>
<IOConfig></IOConfig>
<Dir>in</Dir>
<Bits>16</Bits>
<Attribute>data</Attribute>
</RtlPorts>
<RtlPorts>
<name>w2_address0</name>
<Object>w2</Object>
<Type>array</Type>
<Scope></Scope>
<IOProtocol>ap_memory</IOProtocol>
<IOConfig></IOConfig>
<Dir>out</Dir>
<Bits>2</Bits>
<Attribute>address</Attribute>
</RtlPorts>
<RtlPorts>
<name>w2_ce0</name>
<Object>w2</Object>
<Type>array</Type>
<Scope></Scope>
<IOProtocol>ap_memory</IOProtocol>
<IOConfig></IOConfig>
<Dir>out</Dir>
<Bits>1</Bits>
<Attribute>control</Attribute>
</RtlPorts>
<RtlPorts>
<name>w2_q0</name>
<Object>w2</Object>
<Type>array</Type>
<Scope></Scope>
<IOProtocol>ap_memory</IOProtocol>
<IOConfig></IOConfig>
<Dir>in</Dir>
<Bits>16</Bits>
<Attribute>data</Attribute>
</RtlPorts>
<RtlPorts>
<name>w2_address1</name>
<Object>w2</Object>
<Type>array</Type>
<Scope></Scope>
<IOProtocol>ap_memory</IOProtocol>
<IOConfig></IOConfig>
<Dir>out</Dir>
<Bits>2</Bits>
<Attribute>address</Attribute>
</RtlPorts>
<RtlPorts>
<name>w2_ce1</name>
<Object>w2</Object>
<Type>array</Type>
<Scope></Scope>
<IOProtocol>ap_memory</IOProtocol>
<IOConfig></IOConfig>
<Dir>out</Dir>
<Bits>1</Bits>
<Attribute>control</Attribute>
</RtlPorts>
<RtlPorts>
<name>w2_q1</name>
<Object>w2</Object>
<Type>array</Type>
<Scope></Scope>
<IOProtocol>ap_memory</IOProtocol>
<IOConfig></IOConfig>
<Dir>in</Dir>
<Bits>16</Bits>
<Attribute>data</Attribute>
</RtlPorts>
<RtlPorts>
<name>bias_1_address0</name>
<Object>bias_1</Object>
<Type>array</Type>
<Scope></Scope>
<IOProtocol>ap_memory</IOProtocol>
<IOConfig></IOConfig>
<Dir>out</Dir>
<Bits>1</Bits>
<Attribute>address</Attribute>
</RtlPorts>
<RtlPorts>
<name>bias_1_ce0</name>
<Object>bias_1</Object>
<Type>array</Type>
<Scope></Scope>
<IOProtocol>ap_memory</IOProtocol>
<IOConfig></IOConfig>
<Dir>out</Dir>
<Bits>1</Bits>
<Attribute>control</Attribute>
</RtlPorts>
<RtlPorts>
<name>bias_1_q0</name>
<Object>bias_1</Object>
<Type>array</Type>
<Scope></Scope>
<IOProtocol>ap_memory</IOProtocol>
<IOConfig></IOConfig>
<Dir>in</Dir>
<Bits>16</Bits>
<Attribute>data</Attribute>
</RtlPorts>
<RtlPorts>
<name>bias_2_address0</name>
<Object>bias_2</Object>
<Type>array</Type>
<Scope></Scope>
<IOProtocol>ap_memory</IOProtocol>
<IOConfig></IOConfig>
<Dir>out</Dir>
<Bits>1</Bits>
<Attribute>address</Attribute>
</RtlPorts>
<RtlPorts>
<name>bias_2_ce0</name>
<Object>bias_2</Object>
<Type>array</Type>
<Scope></Scope>
<IOProtocol>ap_memory</IOProtocol>
<IOConfig></IOConfig>
<Dir>out</Dir>
<Bits>1</Bits>
<Attribute>control</Attribute>
</RtlPorts>
<RtlPorts>
<name>bias_2_q0</name>
<Object>bias_2</Object>
<Type>array</Type>
<Scope></Scope>
<IOProtocol>ap_memory</IOProtocol>
<IOConfig></IOConfig>
<Dir>in</Dir>
<Bits>16</Bits>
<Attribute>data</Attribute>
</RtlPorts>
<RtlPorts>
<name>w2_local_3_out</name>
<Object>w2_local_3_out</Object>
<Type>pointer</Type>
<Scope></Scope>
<IOProtocol>ap_vld</IOProtocol>
<IOConfig></IOConfig>
<Dir>out</Dir>
<Bits>16</Bits>
<Attribute>data</Attribute>
</RtlPorts>
<RtlPorts>
<name>w2_local_3_out_ap_vld</name>
<Object>w2_local_3_out</Object>
<Type>pointer</Type>
<Scope></Scope>
<IOProtocol>ap_vld</IOProtocol>
<IOConfig></IOConfig>
<Dir>out</Dir>
<Bits>1</Bits>
<Attribute>control</Attribute>
</RtlPorts>
<RtlPorts>
<name>w2_local_2_out</name>
<Object>w2_local_2_out</Object>
<Type>pointer</Type>
<Scope></Scope>
<IOProtocol>ap_vld</IOProtocol>
<IOConfig></IOConfig>
<Dir>out</Dir>
<Bits>16</Bits>
<Attribute>data</Attribute>
</RtlPorts>
<RtlPorts>
<name>w2_local_2_out_ap_vld</name>
<Object>w2_local_2_out</Object>
<Type>pointer</Type>
<Scope></Scope>
<IOProtocol>ap_vld</IOProtocol>
<IOConfig></IOConfig>
<Dir>out</Dir>
<Bits>1</Bits>
<Attribute>control</Attribute>
</RtlPorts>
<RtlPorts>
<name>w1_local_3_out</name>
<Object>w1_local_3_out</Object>
<Type>pointer</Type>
<Scope></Scope>
<IOProtocol>ap_vld</IOProtocol>
<IOConfig></IOConfig>
<Dir>out</Dir>
<Bits>16</Bits>
<Attribute>data</Attribute>
</RtlPorts>
<RtlPorts>
<name>w1_local_3_out_ap_vld</name>
<Object>w1_local_3_out</Object>
<Type>pointer</Type>
<Scope></Scope>
<IOProtocol>ap_vld</IOProtocol>
<IOConfig></IOConfig>
<Dir>out</Dir>
<Bits>1</Bits>
<Attribute>control</Attribute>
</RtlPorts>
<RtlPorts>
<name>w1_local_2_out</name>
<Object>w1_local_2_out</Object>
<Type>pointer</Type>
<Scope></Scope>
<IOProtocol>ap_vld</IOProtocol>
<IOConfig></IOConfig>
<Dir>out</Dir>
<Bits>16</Bits>
<Attribute>data</Attribute>
</RtlPorts>
<RtlPorts>
<name>w1_local_2_out_ap_vld</name>
<Object>w1_local_2_out</Object>
<Type>pointer</Type>
<Scope></Scope>
<IOProtocol>ap_vld</IOProtocol>
<IOConfig></IOConfig>
<Dir>out</Dir>
<Bits>1</Bits>
<Attribute>control</Attribute>
</RtlPorts>
<RtlPorts>
<name>w2_local_1_out</name>
<Object>w2_local_1_out</Object>
<Type>pointer</Type>
<Scope></Scope>
<IOProtocol>ap_vld</IOProtocol>
<IOConfig></IOConfig>
<Dir>out</Dir>
<Bits>16</Bits>
<Attribute>data</Attribute>
</RtlPorts>
<RtlPorts>
<name>w2_local_1_out_ap_vld</name>
<Object>w2_local_1_out</Object>
<Type>pointer</Type>
<Scope></Scope>
<IOProtocol>ap_vld</IOProtocol>
<IOConfig></IOConfig>
<Dir>out</Dir>
<Bits>1</Bits>
<Attribute>control</Attribute>
</RtlPorts>
<RtlPorts>
<name>w2_local_out</name>
<Object>w2_local_out</Object>
<Type>pointer</Type>
<Scope></Scope>
<IOProtocol>ap_vld</IOProtocol>
<IOConfig></IOConfig>
<Dir>out</Dir>
<Bits>16</Bits>
<Attribute>data</Attribute>
</RtlPorts>
<RtlPorts>
<name>w2_local_out_ap_vld</name>
<Object>w2_local_out</Object>
<Type>pointer</Type>
<Scope></Scope>
<IOProtocol>ap_vld</IOProtocol>
<IOConfig></IOConfig>
<Dir>out</Dir>
<Bits>1</Bits>
<Attribute>control</Attribute>
</RtlPorts>
<RtlPorts>
<name>w1_local_1_out</name>
<Object>w1_local_1_out</Object>
<Type>pointer</Type>
<Scope></Scope>
<IOProtocol>ap_vld</IOProtocol>
<IOConfig></IOConfig>
<Dir>out</Dir>
<Bits>16</Bits>
<Attribute>data</Attribute>
</RtlPorts>
<RtlPorts>
<name>w1_local_1_out_ap_vld</name>
<Object>w1_local_1_out</Object>
<Type>pointer</Type>
<Scope></Scope>
<IOProtocol>ap_vld</IOProtocol>
<IOConfig></IOConfig>
<Dir>out</Dir>
<Bits>1</Bits>
<Attribute>control</Attribute>
</RtlPorts>
<RtlPorts>
<name>w1_local_out</name>
<Object>w1_local_out</Object>
<Type>pointer</Type>
<Scope></Scope>
<IOProtocol>ap_vld</IOProtocol>
<IOConfig></IOConfig>
<Dir>out</Dir>
<Bits>16</Bits>
<Attribute>data</Attribute>
</RtlPorts>
<RtlPorts>
<name>w1_local_out_ap_vld</name>
<Object>w1_local_out</Object>
<Type>pointer</Type>
<Scope></Scope>
<IOProtocol>ap_vld</IOProtocol>
<IOConfig></IOConfig>
<Dir>out</Dir>
<Bits>1</Bits>
<Attribute>control</Attribute>
</RtlPorts>
<RtlPorts>
<name>bias_2_local_idx4_promoted151_out</name>
<Object>bias_2_local_idx4_promoted151_out</Object>
<Type>pointer</Type>
<Scope></Scope>
<IOProtocol>ap_vld</IOProtocol>
<IOConfig></IOConfig>
<Dir>out</Dir>
<Bits>16</Bits>
<Attribute>data</Attribute>
</RtlPorts>
<RtlPorts>
<name>bias_2_local_idx4_promoted151_out_ap_vld</name>
<Object>bias_2_local_idx4_promoted151_out</Object>
<Type>pointer</Type>
<Scope></Scope>
<IOProtocol>ap_vld</IOProtocol>
<IOConfig></IOConfig>
<Dir>out</Dir>
<Bits>1</Bits>
<Attribute>control</Attribute>
</RtlPorts>
<RtlPorts>
<name>bias_2_local_idx_promoted149_out</name>
<Object>bias_2_local_idx_promoted149_out</Object>
<Type>pointer</Type>
<Scope></Scope>
<IOProtocol>ap_vld</IOProtocol>
<IOConfig></IOConfig>
<Dir>out</Dir>
<Bits>16</Bits>
<Attribute>data</Attribute>
</RtlPorts>
<RtlPorts>
<name>bias_2_local_idx_promoted149_out_ap_vld</name>
<Object>bias_2_local_idx_promoted149_out</Object>
<Type>pointer</Type>
<Scope></Scope>
<IOProtocol>ap_vld</IOProtocol>
<IOConfig></IOConfig>
<Dir>out</Dir>
<Bits>1</Bits>
<Attribute>control</Attribute>
</RtlPorts>
<RtlPorts>
<name>bias_1_local_idx1_promoted147_out</name>
<Object>bias_1_local_idx1_promoted147_out</Object>
<Type>pointer</Type>
<Scope></Scope>
<IOProtocol>ap_vld</IOProtocol>
<IOConfig></IOConfig>
<Dir>out</Dir>
<Bits>16</Bits>
<Attribute>data</Attribute>
</RtlPorts>
<RtlPorts>
<name>bias_1_local_idx1_promoted147_out_ap_vld</name>
<Object>bias_1_local_idx1_promoted147_out</Object>
<Type>pointer</Type>
<Scope></Scope>
<IOProtocol>ap_vld</IOProtocol>
<IOConfig></IOConfig>
<Dir>out</Dir>
<Bits>1</Bits>
<Attribute>control</Attribute>
</RtlPorts>
<RtlPorts>
<name>bias_1_local_idx_promoted145_out</name>
<Object>bias_1_local_idx_promoted145_out</Object>
<Type>pointer</Type>
<Scope></Scope>
<IOProtocol>ap_vld</IOProtocol>
<IOConfig></IOConfig>
<Dir>out</Dir>
<Bits>16</Bits>
<Attribute>data</Attribute>
</RtlPorts>
<RtlPorts>
<name>bias_1_local_idx_promoted145_out_ap_vld</name>
<Object>bias_1_local_idx_promoted145_out</Object>
<Type>pointer</Type>
<Scope></Scope>
<IOProtocol>ap_vld</IOProtocol>
<IOConfig></IOConfig>
<Dir>out</Dir>
<Bits>1</Bits>
<Attribute>control</Attribute>
</RtlPorts>
</InterfaceSummary>
</Module>
<Module>
<Name>model_array</Name>
<PerformanceEstimates>
<SummaryOfTimingAnalysis>
<TargetClockPeriod>30.30</TargetClockPeriod>
<ClockUncertainty>6.00</ClockUncertainty>
<TargetInitiationInterval>5</TargetInitiationInterval>
<EstimatedClockPeriod>8.001</EstimatedClockPeriod>
</SummaryOfTimingAnalysis>
<SummaryOfOverallLatency>
<Best-caseLatency>5</Best-caseLatency>
<Average-caseLatency>5</Average-caseLatency>
<Worst-caseLatency>5</Worst-caseLatency>
<Best-caseRealTimeLatency>0.152 us</Best-caseRealTimeLatency>
<Average-caseRealTimeLatency>0.152 us</Average-caseRealTimeLatency>
<Worst-caseRealTimeLatency>0.152 us</Worst-caseRealTimeLatency>
<PipelineInitiationInterval>5</PipelineInitiationInterval>
<PipelineDepth>6</PipelineDepth>
<PipelineType>yes</PipelineType>
</SummaryOfOverallLatency>
<SummaryOfViolations>
<IssueType>-</IssueType>
<ViolationType>-</ViolationType>
<SourceLocation>../weight_pe.cpp:12~../array.cpp:24</SourceLocation>
</SummaryOfViolations>
</PerformanceEstimates>
<AreaEstimates>
<Resources>
<DSP>18</DSP>
<AVAIL_DSP>360</AVAIL_DSP>
<UTIL_DSP>5</UTIL_DSP>
<FF>676</FF>
<AVAIL_FF>141120</AVAIL_FF>
<UTIL_FF>~0</UTIL_FF>
<LUT>570</LUT>
<AVAIL_LUT>70560</AVAIL_LUT>
<UTIL_LUT>~0</UTIL_LUT>
<BRAM_18K>0</BRAM_18K>
<AVAIL_BRAM>432</AVAIL_BRAM>
<UTIL_BRAM>0</UTIL_BRAM>
<URAM>0</URAM>
<AVAIL_URAM>0</AVAIL_URAM>
<UTIL_URAM>0</UTIL_URAM>
</Resources>
</AreaEstimates>
<InterfaceSummary>
<RtlPorts>
<name>ap_clk</name>
<Object>model_array</Object>
<Type>return value</Type>
<Scope></Scope>
<IOProtocol>ap_ctrl_hs</IOProtocol>
<IOConfig></IOConfig>
<Dir>in</Dir>
<Bits>1</Bits>
<Attribute>control</Attribute>
</RtlPorts>
<RtlPorts>
<name>ap_rst</name>
<Object>model_array</Object>
<Type>return value</Type>
<Scope></Scope>
<IOProtocol>ap_ctrl_hs</IOProtocol>
<IOConfig></IOConfig>
<Dir>in</Dir>
<Bits>1</Bits>
<Attribute>control</Attribute>
</RtlPorts>
<RtlPorts>
<name>ap_start</name>
<Object>model_array</Object>
<Type>return value</Type>
<Scope></Scope>
<IOProtocol>ap_ctrl_hs</IOProtocol>
<IOConfig></IOConfig>
<Dir>in</Dir>
<Bits>1</Bits>
<Attribute>control</Attribute>
</RtlPorts>
<RtlPorts>
<name>ap_done</name>
<Object>model_array</Object>
<Type>return value</Type>
<Scope></Scope>
<IOProtocol>ap_ctrl_hs</IOProtocol>
<IOConfig></IOConfig>
<Dir>out</Dir>
<Bits>1</Bits>
<Attribute>control</Attribute>
</RtlPorts>
<RtlPorts>
<name>ap_idle</name>
<Object>model_array</Object>
<Type>return value</Type>
<Scope></Scope>
<IOProtocol>ap_ctrl_hs</IOProtocol>
<IOConfig></IOConfig>
<Dir>out</Dir>
<Bits>1</Bits>
<Attribute>control</Attribute>
</RtlPorts>
<RtlPorts>
<name>ap_ready</name>
<Object>model_array</Object>
<Type>return value</Type>
<Scope></Scope>
<IOProtocol>ap_ctrl_hs</IOProtocol>
<IOConfig></IOConfig>
<Dir>out</Dir>
<Bits>1</Bits>
<Attribute>control</Attribute>
</RtlPorts>
<RtlPorts>
<name>ap_ce</name>
<Object>model_array</Object>
<Type>return value</Type>
<Scope></Scope>
<IOProtocol>ap_ctrl_hs</IOProtocol>
<IOConfig></IOConfig>
<Dir>in</Dir>
<Bits>1</Bits>
<Attribute>control</Attribute>
</RtlPorts>
<RtlPorts>
<name>ap_return_0</name>
<Object>model_array</Object>
<Type>return value</Type>
<Scope></Scope>
<IOProtocol>ap_ctrl_hs</IOProtocol>
<IOConfig></IOConfig>
<Dir>out</Dir>
<Bits>16</Bits>
<Attribute>data</Attribute>
</RtlPorts>
<RtlPorts>
<name>ap_return_1</name>
<Object>model_array</Object>
<Type>return value</Type>
<Scope></Scope>
<IOProtocol>ap_ctrl_hs</IOProtocol>
<IOConfig></IOConfig>
<Dir>out</Dir>
<Bits>16</Bits>
<Attribute>data</Attribute>
</RtlPorts>
<RtlPorts>
<name>ap_return_2</name>
<Object>model_array</Object>
<Type>return value</Type>
<Scope></Scope>
<IOProtocol>ap_ctrl_hs</IOProtocol>
<IOConfig></IOConfig>
<Dir>out</Dir>
<Bits>16</Bits>
<Attribute>data</Attribute>
</RtlPorts>
<RtlPorts>
<name>ap_return_3</name>
<Object>model_array</Object>
<Type>return value</Type>
<Scope></Scope>
<IOProtocol>ap_ctrl_hs</IOProtocol>
<IOConfig></IOConfig>
<Dir>out</Dir>
<Bits>16</Bits>
<Attribute>data</Attribute>
</RtlPorts>
<RtlPorts>
<name>ap_return_4</name>
<Object>model_array</Object>
<Type>return value</Type>
<Scope></Scope>
<IOProtocol>ap_ctrl_hs</IOProtocol>
<IOConfig></IOConfig>
<Dir>out</Dir>
<Bits>16</Bits>
<Attribute>data</Attribute>
</RtlPorts>
<RtlPorts>
<name>ap_return_5</name>
<Object>model_array</Object>
<Type>return value</Type>
<Scope></Scope>
<IOProtocol>ap_ctrl_hs</IOProtocol>
<IOConfig></IOConfig>
<Dir>out</Dir>
<Bits>16</Bits>
<Attribute>data</Attribute>
</RtlPorts>
<RtlPorts>
<name>ap_return_6</name>
<Object>model_array</Object>
<Type>return value</Type>
<Scope></Scope>
<IOProtocol>ap_ctrl_hs</IOProtocol>
<IOConfig></IOConfig>
<Dir>out</Dir>
<Bits>16</Bits>
<Attribute>data</Attribute>
</RtlPorts>
<RtlPorts>
<name>ap_return_7</name>
<Object>model_array</Object>
<Type>return value</Type>
<Scope></Scope>
<IOProtocol>ap_ctrl_hs</IOProtocol>
<IOConfig></IOConfig>
<Dir>out</Dir>
<Bits>16</Bits>
<Attribute>data</Attribute>
</RtlPorts>
<RtlPorts>
<name>ap_return_8</name>
<Object>model_array</Object>
<Type>return value</Type>
<Scope></Scope>
<IOProtocol>ap_ctrl_hs</IOProtocol>
<IOConfig></IOConfig>
<Dir>out</Dir>
<Bits>16</Bits>
<Attribute>data</Attribute>
</RtlPorts>
<RtlPorts>
<name>ap_return_9</name>
<Object>model_array</Object>
<Type>return value</Type>
<Scope></Scope>
<IOProtocol>ap_ctrl_hs</IOProtocol>
<IOConfig></IOConfig>
<Dir>out</Dir>
<Bits>16</Bits>
<Attribute>data</Attribute>
</RtlPorts>
<RtlPorts>
<name>p_read10</name>
<Object>p_read10</Object>
<Type>scalar</Type>
<Scope></Scope>
<IOProtocol>ap_none</IOProtocol>
<IOConfig></IOConfig>
<Dir>in</Dir>
<Bits>16</Bits>
<Attribute>data</Attribute>
</RtlPorts>
<RtlPorts>
<name>p_read29</name>
<Object>p_read29</Object>
<Type>scalar</Type>
<Scope></Scope>
<IOProtocol>ap_none</IOProtocol>
<IOConfig></IOConfig>
<Dir>in</Dir>
<Bits>16</Bits>
<Attribute>data</Attribute>
</RtlPorts>
<RtlPorts>
<name>p_read30</name>
<Object>p_read30</Object>
<Type>scalar</Type>
<Scope></Scope>
<IOProtocol>ap_none</IOProtocol>
<IOConfig></IOConfig>
<Dir>in</Dir>
<Bits>16</Bits>
<Attribute>data</Attribute>
</RtlPorts>
<RtlPorts>
<name>p_read31</name>
<Object>p_read31</Object>
<Type>scalar</Type>
<Scope></Scope>
<IOProtocol>ap_none</IOProtocol>
<IOConfig></IOConfig>
<Dir>in</Dir>
<Bits>16</Bits>
<Attribute>data</Attribute>
</RtlPorts>
<RtlPorts>
<name>biases_0_0_val</name>
<Object>biases_0_0_val</Object>
<Type>scalar</Type>
<Scope></Scope>
<IOProtocol>ap_none</IOProtocol>
<IOConfig></IOConfig>
<Dir>in</Dir>
<Bits>16</Bits>
<Attribute>data</Attribute>
</RtlPorts>
<RtlPorts>
<name>biases_0_1_val</name>
<Object>biases_0_1_val</Object>
<Type>scalar</Type>
<Scope></Scope>
<IOProtocol>ap_none</IOProtocol>
<IOConfig></IOConfig>
<Dir>in</Dir>
<Bits>16</Bits>
<Attribute>data</Attribute>
</RtlPorts>
<RtlPorts>
<name>output_kmin1_0_0_val</name>
<Object>output_kmin1_0_0_val</Object>
<Type>scalar</Type>
<Scope></Scope>
<IOProtocol>ap_none</IOProtocol>
<IOConfig></IOConfig>
<Dir>in</Dir>
<Bits>16</Bits>
<Attribute>data</Attribute>
</RtlPorts>
<RtlPorts>
<name>output_kmin1_0_1_val</name>
<Object>output_kmin1_0_1_val</Object>
<Type>scalar</Type>
<Scope></Scope>
<IOProtocol>ap_none</IOProtocol>
<IOConfig></IOConfig>
<Dir>in</Dir>
<Bits>16</Bits>
<Attribute>data</Attribute>
</RtlPorts>
<RtlPorts>
<name>delta_k_0_0_val</name>
<Object>delta_k_0_0_val</Object>
<Type>scalar</Type>
<Scope></Scope>
<IOProtocol>ap_none</IOProtocol>
<IOConfig></IOConfig>
<Dir>in</Dir>
<Bits>16</Bits>
<Attribute>data</Attribute>
</RtlPorts>
<RtlPorts>
<name>delta_k_0_1_val</name>
<Object>delta_k_0_1_val</Object>
<Type>scalar</Type>
<Scope></Scope>
<IOProtocol>ap_none</IOProtocol>
<IOConfig></IOConfig>
<Dir>in</Dir>
<Bits>16</Bits>
<Attribute>data</Attribute>
</RtlPorts>
<RtlPorts>
<name>training</name>
<Object>training</Object>
<Type>scalar</Type>
<Scope></Scope>
<IOProtocol>ap_none</IOProtocol>
<IOConfig></IOConfig>
<Dir>in</Dir>
<Bits>16</Bits>
<Attribute>data</Attribute>
</RtlPorts>
</InterfaceSummary>
</Module>
<Module>
<Name>accelerator_Pipeline_VITIS_LOOP_65_3</Name>
<Loops>
<VITIS_LOOP_65_3></VITIS_LOOP_65_3>
</Loops>
<PerformanceEstimates>
<SummaryOfTimingAnalysis>
<TargetClockPeriod>30.30</TargetClockPeriod>
<ClockUncertainty>6.00</ClockUncertainty>
<EstimatedClockPeriod>20.707</EstimatedClockPeriod>
</SummaryOfTimingAnalysis>
<SummaryOfOverallLatency>
<Best-caseLatency>83</Best-caseLatency>
<Average-caseLatency>20584</Average-caseLatency>
<Worst-caseLatency>41084</Worst-caseLatency>
<Best-caseRealTimeLatency>2.515 us</Best-caseRealTimeLatency>
<Average-caseRealTimeLatency>0.624 ms</Average-caseRealTimeLatency>
<Worst-caseRealTimeLatency>1.245 ms</Worst-caseRealTimeLatency>
<PipelineInitiationInterval>83 ~ 41084</PipelineInitiationInterval>
<PipelineType>no</PipelineType>
</SummaryOfOverallLatency>
<SummaryOfLoopLatency>
<VITIS_LOOP_65_3>
<Name>VITIS_LOOP_65_3</Name>
<Slack>24.30</Slack>
<TripCount>
<range>
<min>0</min>
<max>500</max>
</range>
</TripCount>
<Latency>81 ~ 41081</Latency>
<AbsoluteTimeLatency>2.455 us ~ 1.245 ms</AbsoluteTimeLatency>
<PipelineII>82</PipelineII>
<PipelineDepth>82</PipelineDepth>
<PipelineType>yes</PipelineType>
<InstanceList>
<Instance>grp_model_array_fu_596</Instance>
</InstanceList>
</VITIS_LOOP_65_3>
</SummaryOfLoopLatency>
<SummaryOfViolations>
<IssueType>-</IssueType>
<ViolationType>-</ViolationType>
<SourceLocation>../accelerator.cpp:64</SourceLocation>
<SummaryOfLoopViolations>
<VITIS_LOOP_65_3>
<Name>VITIS_LOOP_65_3</Name>
<IssueType>-</IssueType>
<ViolationType>-</ViolationType>
<SourceLocation>../accelerator.cpp:65</SourceLocation>
</VITIS_LOOP_65_3>
</SummaryOfLoopViolations>
</SummaryOfViolations>
</PerformanceEstimates>
<AreaEstimates>
<Resources>
<DSP>18</DSP>
<AVAIL_DSP>360</AVAIL_DSP>
<UTIL_DSP>5</UTIL_DSP>
<FF>2375</FF>
<AVAIL_FF>141120</AVAIL_FF>
<UTIL_FF>1</UTIL_FF>
<LUT>6067</LUT>
<AVAIL_LUT>70560</AVAIL_LUT>
<UTIL_LUT>8</UTIL_LUT>
<BRAM_18K>0</BRAM_18K>
<AVAIL_BRAM>432</AVAIL_BRAM>
<UTIL_BRAM>0</UTIL_BRAM>
<URAM>0</URAM>
<AVAIL_URAM>0</AVAIL_URAM>
<UTIL_URAM>0</UTIL_URAM>
</Resources>
</AreaEstimates>
<InterfaceSummary>
<RtlPorts>
<name>ap_clk</name>
<Object>accelerator_Pipeline_VITIS_LOOP_65_3</Object>
<Type>return value</Type>
<Scope></Scope>
<IOProtocol>ap_ctrl_hs</IOProtocol>
<IOConfig></IOConfig>
<Dir>in</Dir>
<Bits>1</Bits>
<Attribute>control</Attribute>
</RtlPorts>
<RtlPorts>
<name>ap_rst</name>
<Object>accelerator_Pipeline_VITIS_LOOP_65_3</Object>
<Type>return value</Type>
<Scope></Scope>
<IOProtocol>ap_ctrl_hs</IOProtocol>
<IOConfig></IOConfig>
<Dir>in</Dir>
<Bits>1</Bits>
<Attribute>control</Attribute>
</RtlPorts>
<RtlPorts>
<name>ap_start</name>
<Object>accelerator_Pipeline_VITIS_LOOP_65_3</Object>
<Type>return value</Type>
<Scope></Scope>
<IOProtocol>ap_ctrl_hs</IOProtocol>
<IOConfig></IOConfig>
<Dir>in</Dir>
<Bits>1</Bits>
<Attribute>control</Attribute>
</RtlPorts>
<RtlPorts>
<name>ap_done</name>
<Object>accelerator_Pipeline_VITIS_LOOP_65_3</Object>
<Type>return value</Type>
<Scope></Scope>
<IOProtocol>ap_ctrl_hs</IOProtocol>
<IOConfig></IOConfig>
<Dir>out</Dir>
<Bits>1</Bits>
<Attribute>control</Attribute>
</RtlPorts>
<RtlPorts>
<name>ap_idle</name>
<Object>accelerator_Pipeline_VITIS_LOOP_65_3</Object>
<Type>return value</Type>
<Scope></Scope>
<IOProtocol>ap_ctrl_hs</IOProtocol>
<IOConfig></IOConfig>
<Dir>out</Dir>
<Bits>1</Bits>
<Attribute>control</Attribute>
</RtlPorts>
<RtlPorts>
<name>ap_ready</name>
<Object>accelerator_Pipeline_VITIS_LOOP_65_3</Object>
<Type>return value</Type>
<Scope></Scope>
<IOProtocol>ap_ctrl_hs</IOProtocol>
<IOConfig></IOConfig>
<Dir>out</Dir>
<Bits>1</Bits>
<Attribute>control</Attribute>
</RtlPorts>
<RtlPorts>
<name>ap_return</name>
<Object>accelerator_Pipeline_VITIS_LOOP_65_3</Object>
<Type>return value</Type>
<Scope></Scope>
<IOProtocol>ap_ctrl_hs</IOProtocol>
<IOConfig></IOConfig>
<Dir>out</Dir>
<Bits>1</Bits>
<Attribute>data</Attribute>
</RtlPorts>
<RtlPorts>
<name>w2_local_1_reload</name>
<Object>w2_local_1_reload</Object>
<Type>scalar</Type>
<Scope></Scope>
<IOProtocol>ap_none</IOProtocol>
<IOConfig></IOConfig>
<Dir>in</Dir>
<Bits>16</Bits>
<Attribute>data</Attribute>
</RtlPorts>
<RtlPorts>
<name>w2_local_reload</name>
<Object>w2_local_reload</Object>
<Type>scalar</Type>
<Scope></Scope>
<IOProtocol>ap_none</IOProtocol>
<IOConfig></IOConfig>
<Dir>in</Dir>
<Bits>16</Bits>
<Attribute>data</Attribute>
</RtlPorts>
<RtlPorts>
<name>w2_local_3_reload</name>
<Object>w2_local_3_reload</Object>
<Type>scalar</Type>
<Scope></Scope>
<IOProtocol>ap_none</IOProtocol>
<IOConfig></IOConfig>
<Dir>in</Dir>
<Bits>16</Bits>
<Attribute>data</Attribute>
</RtlPorts>
<RtlPorts>
<name>w2_local_2_reload</name>
<Object>w2_local_2_reload</Object>
<Type>scalar</Type>
<Scope></Scope>
<IOProtocol>ap_none</IOProtocol>
<IOConfig></IOConfig>
<Dir>in</Dir>
<Bits>16</Bits>
<Attribute>data</Attribute>
</RtlPorts>
<RtlPorts>
<name>w1_local_1_reload</name>
<Object>w1_local_1_reload</Object>
<Type>scalar</Type>
<Scope></Scope>
<IOProtocol>ap_none</IOProtocol>
<IOConfig></IOConfig>
<Dir>in</Dir>
<Bits>16</Bits>
<Attribute>data</Attribute>
</RtlPorts>
<RtlPorts>
<name>w1_local_reload</name>
<Object>w1_local_reload</Object>
<Type>scalar</Type>
<Scope></Scope>
<IOProtocol>ap_none</IOProtocol>
<IOConfig></IOConfig>
<Dir>in</Dir>
<Bits>16</Bits>
<Attribute>data</Attribute>
</RtlPorts>
<RtlPorts>
<name>w1_local_3_reload</name>
<Object>w1_local_3_reload</Object>
<Type>scalar</Type>
<Scope></Scope>
<IOProtocol>ap_none</IOProtocol>
<IOConfig></IOConfig>
<Dir>in</Dir>
<Bits>16</Bits>
<Attribute>data</Attribute>
</RtlPorts>
<RtlPorts>
<name>w1_local_2_reload</name>
<Object>w1_local_2_reload</Object>
<Type>scalar</Type>
<Scope></Scope>
<IOProtocol>ap_none</IOProtocol>
<IOConfig></IOConfig>
<Dir>in</Dir>
<Bits>16</Bits>
<Attribute>data</Attribute>
</RtlPorts>
<RtlPorts>
<name>bias_2_local_idx4_promoted151_reload</name>
<Object>bias_2_local_idx4_promoted151_reload</Object>
<Type>scalar</Type>
<Scope></Scope>
<IOProtocol>ap_none</IOProtocol>
<IOConfig></IOConfig>
<Dir>in</Dir>
<Bits>16</Bits>
<Attribute>data</Attribute>
</RtlPorts>
<RtlPorts>
<name>bias_2_local_idx_promoted149_reload</name>
<Object>bias_2_local_idx_promoted149_reload</Object>
<Type>scalar</Type>
<Scope></Scope>
<IOProtocol>ap_none</IOProtocol>
<IOConfig></IOConfig>
<Dir>in</Dir>
<Bits>16</Bits>
<Attribute>data</Attribute>
</RtlPorts>
<RtlPorts>
<name>bias_1_local_idx1_promoted147_reload</name>
<Object>bias_1_local_idx1_promoted147_reload</Object>
<Type>scalar</Type>
<Scope></Scope>
<IOProtocol>ap_none</IOProtocol>
<IOConfig></IOConfig>
<Dir>in</Dir>
<Bits>16</Bits>
<Attribute>data</Attribute>
</RtlPorts>
<RtlPorts>
<name>bias_1_local_idx_promoted145_reload</name>
<Object>bias_1_local_idx_promoted145_reload</Object>
<Type>scalar</Type>
<Scope></Scope>
<IOProtocol>ap_none</IOProtocol>
<IOConfig></IOConfig>
<Dir>in</Dir>
<Bits>16</Bits>
<Attribute>data</Attribute>
</RtlPorts>
<RtlPorts>
<name>training</name>
<Object>training</Object>
<Type>scalar</Type>
<Scope></Scope>
<IOProtocol>ap_none</IOProtocol>
<IOConfig></IOConfig>
<Dir>in</Dir>
<Bits>16</Bits>
<Attribute>data</Attribute>
</RtlPorts>
<RtlPorts>
<name>cmp_i_i</name>
<Object>cmp_i_i</Object>
<Type>scalar</Type>
<Scope></Scope>
<IOProtocol>ap_none</IOProtocol>
<IOConfig></IOConfig>
<Dir>in</Dir>
<Bits>1</Bits>
<Attribute>data</Attribute>
</RtlPorts>
<RtlPorts>
<name>w2_local_3_0_out</name>
<Object>w2_local_3_0_out</Object>
<Type>pointer</Type>
<Scope></Scope>
<IOProtocol>ap_vld</IOProtocol>
<IOConfig></IOConfig>
<Dir>out</Dir>
<Bits>16</Bits>
<Attribute>data</Attribute>
</RtlPorts>
<RtlPorts>
<name>w2_local_3_0_out_ap_vld</name>
<Object>w2_local_3_0_out</Object>
<Type>pointer</Type>
<Scope></Scope>
<IOProtocol>ap_vld</IOProtocol>
<IOConfig></IOConfig>
<Dir>out</Dir>
<Bits>1</Bits>
<Attribute>control</Attribute>
</RtlPorts>
<RtlPorts>
<name>w2_local_2_0_out</name>
<Object>w2_local_2_0_out</Object>
<Type>pointer</Type>
<Scope></Scope>
<IOProtocol>ap_vld</IOProtocol>
<IOConfig></IOConfig>
<Dir>out</Dir>
<Bits>16</Bits>
<Attribute>data</Attribute>
</RtlPorts>
<RtlPorts>
<name>w2_local_2_0_out_ap_vld</name>
<Object>w2_local_2_0_out</Object>
<Type>pointer</Type>
<Scope></Scope>
<IOProtocol>ap_vld</IOProtocol>
<IOConfig></IOConfig>
<Dir>out</Dir>
<Bits>1</Bits>
<Attribute>control</Attribute>
</RtlPorts>
<RtlPorts>
<name>w2_local_1_0_out</name>
<Object>w2_local_1_0_out</Object>
<Type>pointer</Type>
<Scope></Scope>
<IOProtocol>ap_vld</IOProtocol>
<IOConfig></IOConfig>
<Dir>out</Dir>
<Bits>16</Bits>
<Attribute>data</Attribute>
</RtlPorts>
<RtlPorts>
<name>w2_local_1_0_out_ap_vld</name>
<Object>w2_local_1_0_out</Object>
<Type>pointer</Type>
<Scope></Scope>
<IOProtocol>ap_vld</IOProtocol>
<IOConfig></IOConfig>
<Dir>out</Dir>
<Bits>1</Bits>
<Attribute>control</Attribute>
</RtlPorts>
<RtlPorts>
<name>w2_local_0_out</name>
<Object>w2_local_0_out</Object>
<Type>pointer</Type>
<Scope></Scope>
<IOProtocol>ap_vld</IOProtocol>
<IOConfig></IOConfig>
<Dir>out</Dir>
<Bits>16</Bits>
<Attribute>data</Attribute>
</RtlPorts>
<RtlPorts>
<name>w2_local_0_out_ap_vld</name>
<Object>w2_local_0_out</Object>
<Type>pointer</Type>
<Scope></Scope>
<IOProtocol>ap_vld</IOProtocol>
<IOConfig></IOConfig>
<Dir>out</Dir>
<Bits>1</Bits>
<Attribute>control</Attribute>
</RtlPorts>
<RtlPorts>
<name>w1_local_3_0_out</name>
<Object>w1_local_3_0_out</Object>
<Type>pointer</Type>
<Scope></Scope>
<IOProtocol>ap_vld</IOProtocol>
<IOConfig></IOConfig>
<Dir>out</Dir>
<Bits>16</Bits>
<Attribute>data</Attribute>
</RtlPorts>
<RtlPorts>
<name>w1_local_3_0_out_ap_vld</name>
<Object>w1_local_3_0_out</Object>
<Type>pointer</Type>
<Scope></Scope>
<IOProtocol>ap_vld</IOProtocol>
<IOConfig></IOConfig>
<Dir>out</Dir>
<Bits>1</Bits>
<Attribute>control</Attribute>
</RtlPorts>
<RtlPorts>
<name>w1_local_2_0_out</name>
<Object>w1_local_2_0_out</Object>
<Type>pointer</Type>
<Scope></Scope>
<IOProtocol>ap_vld</IOProtocol>
<IOConfig></IOConfig>
<Dir>out</Dir>
<Bits>16</Bits>
<Attribute>data</Attribute>
</RtlPorts>
<RtlPorts>
<name>w1_local_2_0_out_ap_vld</name>
<Object>w1_local_2_0_out</Object>
<Type>pointer</Type>
<Scope></Scope>
<IOProtocol>ap_vld</IOProtocol>
<IOConfig></IOConfig>
<Dir>out</Dir>
<Bits>1</Bits>
<Attribute>control</Attribute>
</RtlPorts>
<RtlPorts>
<name>w1_local_1_0_out</name>
<Object>w1_local_1_0_out</Object>
<Type>pointer</Type>
<Scope></Scope>
<IOProtocol>ap_vld</IOProtocol>
<IOConfig></IOConfig>
<Dir>out</Dir>
<Bits>16</Bits>
<Attribute>data</Attribute>
</RtlPorts>
<RtlPorts>
<name>w1_local_1_0_out_ap_vld</name>
<Object>w1_local_1_0_out</Object>
<Type>pointer</Type>
<Scope></Scope>
<IOProtocol>ap_vld</IOProtocol>
<IOConfig></IOConfig>
<Dir>out</Dir>
<Bits>1</Bits>
<Attribute>control</Attribute>
</RtlPorts>
<RtlPorts>
<name>w1_local_0_out</name>
<Object>w1_local_0_out</Object>
<Type>pointer</Type>
<Scope></Scope>
<IOProtocol>ap_vld</IOProtocol>
<IOConfig></IOConfig>
<Dir>out</Dir>
<Bits>16</Bits>
<Attribute>data</Attribute>
</RtlPorts>
<RtlPorts>
<name>w1_local_0_out_ap_vld</name>
<Object>w1_local_0_out</Object>
<Type>pointer</Type>
<Scope></Scope>
<IOProtocol>ap_vld</IOProtocol>
<IOConfig></IOConfig>
<Dir>out</Dir>
<Bits>1</Bits>
<Attribute>control</Attribute>
</RtlPorts>
<RtlPorts>
<name>bias_2_local_idx4_val110_out</name>
<Object>bias_2_local_idx4_val110_out</Object>
<Type>pointer</Type>
<Scope></Scope>
<IOProtocol>ap_vld</IOProtocol>
<IOConfig></IOConfig>
<Dir>out</Dir>
<Bits>16</Bits>
<Attribute>data</Attribute>
</RtlPorts>
<RtlPorts>
<name>bias_2_local_idx4_val110_out_ap_vld</name>
<Object>bias_2_local_idx4_val110_out</Object>
<Type>pointer</Type>
<Scope></Scope>
<IOProtocol>ap_vld</IOProtocol>
<IOConfig></IOConfig>
<Dir>out</Dir>
<Bits>1</Bits>
<Attribute>control</Attribute>
</RtlPorts>
<RtlPorts>
<name>bias_2_local_idx_val109_out</name>
<Object>bias_2_local_idx_val109_out</Object>
<Type>pointer</Type>
<Scope></Scope>
<IOProtocol>ap_vld</IOProtocol>
<IOConfig></IOConfig>
<Dir>out</Dir>
<Bits>16</Bits>
<Attribute>data</Attribute>
</RtlPorts>
<RtlPorts>
<name>bias_2_local_idx_val109_out_ap_vld</name>
<Object>bias_2_local_idx_val109_out</Object>
<Type>pointer</Type>
<Scope></Scope>
<IOProtocol>ap_vld</IOProtocol>
<IOConfig></IOConfig>
<Dir>out</Dir>
<Bits>1</Bits>
<Attribute>control</Attribute>
</RtlPorts>
<RtlPorts>
<name>bias_1_local_idx1_val108_out</name>
<Object>bias_1_local_idx1_val108_out</Object>
<Type>pointer</Type>
<Scope></Scope>
<IOProtocol>ap_vld</IOProtocol>
<IOConfig></IOConfig>
<Dir>out</Dir>
<Bits>16</Bits>
<Attribute>data</Attribute>
</RtlPorts>
<RtlPorts>
<name>bias_1_local_idx1_val108_out_ap_vld</name>
<Object>bias_1_local_idx1_val108_out</Object>
<Type>pointer</Type>
<Scope></Scope>
<IOProtocol>ap_vld</IOProtocol>
<IOConfig></IOConfig>
<Dir>out</Dir>
<Bits>1</Bits>
<Attribute>control</Attribute>
</RtlPorts>
<RtlPorts>
<name>bias_1_local_idx_val107_out</name>
<Object>bias_1_local_idx_val107_out</Object>
<Type>pointer</Type>
<Scope></Scope>
<IOProtocol>ap_vld</IOProtocol>
<IOConfig></IOConfig>
<Dir>out</Dir>
<Bits>16</Bits>
<Attribute>data</Attribute>
</RtlPorts>
<RtlPorts>
<name>bias_1_local_idx_val107_out_ap_vld</name>
<Object>bias_1_local_idx_val107_out</Object>
<Type>pointer</Type>
<Scope></Scope>
<IOProtocol>ap_vld</IOProtocol>
<IOConfig></IOConfig>
<Dir>out</Dir>
<Bits>1</Bits>
<Attribute>control</Attribute>
</RtlPorts>
<RtlPorts>
<name>output_array_inference_3_out</name>
<Object>output_array_inference_3_out</Object>
<Type>pointer</Type>
<Scope></Scope>
<IOProtocol>ap_vld</IOProtocol>
<IOConfig></IOConfig>
<Dir>out</Dir>
<Bits>16</Bits>
<Attribute>data</Attribute>
</RtlPorts>
<RtlPorts>
<name>output_array_inference_3_out_ap_vld</name>
<Object>output_array_inference_3_out</Object>
<Type>pointer</Type>
<Scope></Scope>
<IOProtocol>ap_vld</IOProtocol>
<IOConfig></IOConfig>
<Dir>out</Dir>
<Bits>1</Bits>
<Attribute>control</Attribute>
</RtlPorts>
<RtlPorts>
<name>output_array_inference_2_out</name>
<Object>output_array_inference_2_out</Object>
<Type>pointer</Type>
<Scope></Scope>
<IOProtocol>ap_vld</IOProtocol>
<IOConfig></IOConfig>
<Dir>out</Dir>
<Bits>16</Bits>
<Attribute>data</Attribute>
</RtlPorts>
<RtlPorts>
<name>output_array_inference_2_out_ap_vld</name>
<Object>output_array_inference_2_out</Object>
<Type>pointer</Type>
<Scope></Scope>
<IOProtocol>ap_vld</IOProtocol>
<IOConfig></IOConfig>
<Dir>out</Dir>
<Bits>1</Bits>
<Attribute>control</Attribute>
</RtlPorts>
<RtlPorts>
<name>output_array_inference_1_out</name>
<Object>output_array_inference_1_out</Object>
<Type>pointer</Type>
<Scope></Scope>
<IOProtocol>ap_vld</IOProtocol>
<IOConfig></IOConfig>
<Dir>out</Dir>
<Bits>16</Bits>
<Attribute>data</Attribute>
</RtlPorts>
<RtlPorts>
<name>output_array_inference_1_out_ap_vld</name>
<Object>output_array_inference_1_out</Object>
<Type>pointer</Type>
<Scope></Scope>
<IOProtocol>ap_vld</IOProtocol>
<IOConfig></IOConfig>
<Dir>out</Dir>
<Bits>1</Bits>
<Attribute>control</Attribute>
</RtlPorts>
<RtlPorts>
<name>output_array_inference_out</name>
<Object>output_array_inference_out</Object>
<Type>pointer</Type>
<Scope></Scope>
<IOProtocol>ap_vld</IOProtocol>
<IOConfig></IOConfig>
<Dir>out</Dir>
<Bits>16</Bits>
<Attribute>data</Attribute>
</RtlPorts>
<RtlPorts>
<name>output_array_inference_out_ap_vld</name>
<Object>output_array_inference_out</Object>
<Type>pointer</Type>
<Scope></Scope>
<IOProtocol>ap_vld</IOProtocol>
<IOConfig></IOConfig>
<Dir>out</Dir>
<Bits>1</Bits>
<Attribute>control</Attribute>
</RtlPorts>
<RtlPorts>
<name>output_array_inference_4_out</name>
<Object>output_array_inference_4_out</Object>
<Type>pointer</Type>
<Scope></Scope>
<IOProtocol>ap_vld</IOProtocol>
<IOConfig></IOConfig>
<Dir>out</Dir>
<Bits>16</Bits>
<Attribute>data</Attribute>
</RtlPorts>
<RtlPorts>
<name>output_array_inference_4_out_ap_vld</name>
<Object>output_array_inference_4_out</Object>
<Type>pointer</Type>
<Scope></Scope>
<IOProtocol>ap_vld</IOProtocol>
<IOConfig></IOConfig>
<Dir>out</Dir>
<Bits>1</Bits>
<Attribute>control</Attribute>
</RtlPorts>
<RtlPorts>
<name>output_array_inference_5_out</name>
<Object>output_array_inference_5_out</Object>
<Type>pointer</Type>
<Scope></Scope>
<IOProtocol>ap_vld</IOProtocol>
<IOConfig></IOConfig>
<Dir>out</Dir>
<Bits>16</Bits>
<Attribute>data</Attribute>
</RtlPorts>
<RtlPorts>
<name>output_array_inference_5_out_ap_vld</name>
<Object>output_array_inference_5_out</Object>
<Type>pointer</Type>
<Scope></Scope>
<IOProtocol>ap_vld</IOProtocol>
<IOConfig></IOConfig>
<Dir>out</Dir>
<Bits>1</Bits>
<Attribute>control</Attribute>
</RtlPorts>
<RtlPorts>
<name>output_array_inference_6_out</name>
<Object>output_array_inference_6_out</Object>
<Type>pointer</Type>
<Scope></Scope>
<IOProtocol>ap_vld</IOProtocol>
<IOConfig></IOConfig>
<Dir>out</Dir>
<Bits>16</Bits>
<Attribute>data</Attribute>
</RtlPorts>
<RtlPorts>
<name>output_array_inference_6_out_ap_vld</name>
<Object>output_array_inference_6_out</Object>
<Type>pointer</Type>
<Scope></Scope>
<IOProtocol>ap_vld</IOProtocol>
<IOConfig></IOConfig>
<Dir>out</Dir>
<Bits>1</Bits>
<Attribute>control</Attribute>
</RtlPorts>
<RtlPorts>
<name>output_array_inference_7_out</name>
<Object>output_array_inference_7_out</Object>
<Type>pointer</Type>
<Scope></Scope>
<IOProtocol>ap_vld</IOProtocol>
<IOConfig></IOConfig>
<Dir>out</Dir>
<Bits>16</Bits>
<Attribute>data</Attribute>
</RtlPorts>
<RtlPorts>
<name>output_array_inference_7_out_ap_vld</name>
<Object>output_array_inference_7_out</Object>
<Type>pointer</Type>
<Scope></Scope>
<IOProtocol>ap_vld</IOProtocol>
<IOConfig></IOConfig>
<Dir>out</Dir>
<Bits>1</Bits>
<Attribute>control</Attribute>
</RtlPorts>
<RtlPorts>
<name>array_back2_weight_changes_24_out</name>
<Object>array_back2_weight_changes_24_out</Object>
<Type>pointer</Type>
<Scope></Scope>
<IOProtocol>ap_vld</IOProtocol>
<IOConfig></IOConfig>
<Dir>out</Dir>
<Bits>16</Bits>
<Attribute>data</Attribute>
</RtlPorts>
<RtlPorts>
<name>array_back2_weight_changes_24_out_ap_vld</name>
<Object>array_back2_weight_changes_24_out</Object>
<Type>pointer</Type>
<Scope></Scope>
<IOProtocol>ap_vld</IOProtocol>
<IOConfig></IOConfig>
<Dir>out</Dir>
<Bits>1</Bits>
<Attribute>control</Attribute>
</RtlPorts>
<RtlPorts>
<name>array_back2_weight_changes_25_out</name>
<Object>array_back2_weight_changes_25_out</Object>
<Type>pointer</Type>
<Scope></Scope>
<IOProtocol>ap_vld</IOProtocol>
<IOConfig></IOConfig>
<Dir>out</Dir>
<Bits>16</Bits>
<Attribute>data</Attribute>
</RtlPorts>
<RtlPorts>
<name>array_back2_weight_changes_25_out_ap_vld</name>
<Object>array_back2_weight_changes_25_out</Object>
<Type>pointer</Type>
<Scope></Scope>
<IOProtocol>ap_vld</IOProtocol>
<IOConfig></IOConfig>
<Dir>out</Dir>
<Bits>1</Bits>
<Attribute>control</Attribute>
</RtlPorts>
<RtlPorts>
<name>array_back2_weight_changes_26_out</name>
<Object>array_back2_weight_changes_26_out</Object>
<Type>pointer</Type>
<Scope></Scope>
<IOProtocol>ap_vld</IOProtocol>
<IOConfig></IOConfig>
<Dir>out</Dir>
<Bits>16</Bits>
<Attribute>data</Attribute>
</RtlPorts>
<RtlPorts>
<name>array_back2_weight_changes_26_out_ap_vld</name>
<Object>array_back2_weight_changes_26_out</Object>
<Type>pointer</Type>
<Scope></Scope>
<IOProtocol>ap_vld</IOProtocol>
<IOConfig></IOConfig>
<Dir>out</Dir>
<Bits>1</Bits>
<Attribute>control</Attribute>
</RtlPorts>
<RtlPorts>
<name>array_back2_weight_changes_27_out</name>
<Object>array_back2_weight_changes_27_out</Object>
<Type>pointer</Type>
<Scope></Scope>
<IOProtocol>ap_vld</IOProtocol>
<IOConfig></IOConfig>
<Dir>out</Dir>
<Bits>16</Bits>
<Attribute>data</Attribute>
</RtlPorts>
<RtlPorts>
<name>array_back2_weight_changes_27_out_ap_vld</name>
<Object>array_back2_weight_changes_27_out</Object>
<Type>pointer</Type>
<Scope></Scope>
<IOProtocol>ap_vld</IOProtocol>
<IOConfig></IOConfig>
<Dir>out</Dir>
<Bits>1</Bits>
<Attribute>control</Attribute>
</RtlPorts>
<RtlPorts>
<name>array_back2_bias_change_8_out</name>
<Object>array_back2_bias_change_8_out</Object>
<Type>pointer</Type>
<Scope></Scope>
<IOProtocol>ap_vld</IOProtocol>
<IOConfig></IOConfig>
<Dir>out</Dir>
<Bits>16</Bits>
<Attribute>data</Attribute>
</RtlPorts>
<RtlPorts>
<name>array_back2_bias_change_8_out_ap_vld</name>
<Object>array_back2_bias_change_8_out</Object>
<Type>pointer</Type>
<Scope></Scope>
<IOProtocol>ap_vld</IOProtocol>
<IOConfig></IOConfig>
<Dir>out</Dir>
<Bits>1</Bits>
<Attribute>control</Attribute>
</RtlPorts>
<RtlPorts>
<name>array_back2_bias_change_9_out</name>
<Object>array_back2_bias_change_9_out</Object>
<Type>pointer</Type>
<Scope></Scope>
<IOProtocol>ap_vld</IOProtocol>
<IOConfig></IOConfig>
<Dir>out</Dir>
<Bits>16</Bits>
<Attribute>data</Attribute>
</RtlPorts>
<RtlPorts>
<name>array_back2_bias_change_9_out_ap_vld</name>
<Object>array_back2_bias_change_9_out</Object>
<Type>pointer</Type>
<Scope></Scope>
<IOProtocol>ap_vld</IOProtocol>
<IOConfig></IOConfig>
<Dir>out</Dir>
<Bits>1</Bits>
<Attribute>control</Attribute>
</RtlPorts>
<RtlPorts>
<name>array_back1_weight_changes_24_out</name>
<Object>array_back1_weight_changes_24_out</Object>
<Type>pointer</Type>
<Scope></Scope>
<IOProtocol>ap_vld</IOProtocol>
<IOConfig></IOConfig>
<Dir>out</Dir>
<Bits>16</Bits>
<Attribute>data</Attribute>
</RtlPorts>
<RtlPorts>
<name>array_back1_weight_changes_24_out_ap_vld</name>
<Object>array_back1_weight_changes_24_out</Object>
<Type>pointer</Type>
<Scope></Scope>
<IOProtocol>ap_vld</IOProtocol>
<IOConfig></IOConfig>
<Dir>out</Dir>
<Bits>1</Bits>
<Attribute>control</Attribute>
</RtlPorts>
<RtlPorts>
<name>array_back1_weight_changes_25_out</name>
<Object>array_back1_weight_changes_25_out</Object>
<Type>pointer</Type>
<Scope></Scope>
<IOProtocol>ap_vld</IOProtocol>
<IOConfig></IOConfig>
<Dir>out</Dir>
<Bits>16</Bits>
<Attribute>data</Attribute>
</RtlPorts>
<RtlPorts>
<name>array_back1_weight_changes_25_out_ap_vld</name>
<Object>array_back1_weight_changes_25_out</Object>
<Type>pointer</Type>
<Scope></Scope>
<IOProtocol>ap_vld</IOProtocol>
<IOConfig></IOConfig>
<Dir>out</Dir>
<Bits>1</Bits>
<Attribute>control</Attribute>
</RtlPorts>
<RtlPorts>
<name>array_back1_weight_changes_26_out</name>
<Object>array_back1_weight_changes_26_out</Object>
<Type>pointer</Type>
<Scope></Scope>
<IOProtocol>ap_vld</IOProtocol>
<IOConfig></IOConfig>
<Dir>out</Dir>
<Bits>16</Bits>
<Attribute>data</Attribute>
</RtlPorts>
<RtlPorts>
<name>array_back1_weight_changes_26_out_ap_vld</name>
<Object>array_back1_weight_changes_26_out</Object>
<Type>pointer</Type>
<Scope></Scope>
<IOProtocol>ap_vld</IOProtocol>
<IOConfig></IOConfig>
<Dir>out</Dir>
<Bits>1</Bits>
<Attribute>control</Attribute>
</RtlPorts>
<RtlPorts>
<name>array_back1_weight_changes_27_out</name>
<Object>array_back1_weight_changes_27_out</Object>
<Type>pointer</Type>
<Scope></Scope>
<IOProtocol>ap_vld</IOProtocol>
<IOConfig></IOConfig>
<Dir>out</Dir>
<Bits>16</Bits>
<Attribute>data</Attribute>
</RtlPorts>
<RtlPorts>
<name>array_back1_weight_changes_27_out_ap_vld</name>
<Object>array_back1_weight_changes_27_out</Object>
<Type>pointer</Type>
<Scope></Scope>
<IOProtocol>ap_vld</IOProtocol>
<IOConfig></IOConfig>
<Dir>out</Dir>
<Bits>1</Bits>
<Attribute>control</Attribute>
</RtlPorts>
<RtlPorts>
<name>array_back1_bias_change_8_out</name>
<Object>array_back1_bias_change_8_out</Object>
<Type>pointer</Type>
<Scope></Scope>
<IOProtocol>ap_vld</IOProtocol>
<IOConfig></IOConfig>
<Dir>out</Dir>
<Bits>16</Bits>
<Attribute>data</Attribute>
</RtlPorts>
<RtlPorts>
<name>array_back1_bias_change_8_out_ap_vld</name>
<Object>array_back1_bias_change_8_out</Object>
<Type>pointer</Type>
<Scope></Scope>
<IOProtocol>ap_vld</IOProtocol>
<IOConfig></IOConfig>
<Dir>out</Dir>
<Bits>1</Bits>
<Attribute>control</Attribute>
</RtlPorts>
<RtlPorts>
<name>array_back1_bias_change_9_out</name>
<Object>array_back1_bias_change_9_out</Object>
<Type>pointer</Type>
<Scope></Scope>
<IOProtocol>ap_vld</IOProtocol>
<IOConfig></IOConfig>
<Dir>out</Dir>
<Bits>16</Bits>
<Attribute>data</Attribute>
</RtlPorts>
<RtlPorts>
<name>array_back1_bias_change_9_out_ap_vld</name>
<Object>array_back1_bias_change_9_out</Object>
<Type>pointer</Type>
<Scope></Scope>
<IOProtocol>ap_vld</IOProtocol>
<IOConfig></IOConfig>
<Dir>out</Dir>
<Bits>1</Bits>
<Attribute>control</Attribute>
</RtlPorts>
</InterfaceSummary>
</Module>
<Module>
<Name>accelerator_Pipeline_VITIS_LOOP_157_9</Name>
<Loops>
<VITIS_LOOP_157_9></VITIS_LOOP_157_9>
</Loops>
<PerformanceEstimates>
<SummaryOfTimingAnalysis>
<TargetClockPeriod>30.30</TargetClockPeriod>
<ClockUncertainty>6.00</ClockUncertainty>
<EstimatedClockPeriod>1.954</EstimatedClockPeriod>
</SummaryOfTimingAnalysis>
<SummaryOfOverallLatency>
<Best-caseLatency>4</Best-caseLatency>
<Average-caseLatency>4</Average-caseLatency>
<Worst-caseLatency>4</Worst-caseLatency>
<Best-caseRealTimeLatency>0.121 us</Best-caseRealTimeLatency>
<Average-caseRealTimeLatency>0.121 us</Average-caseRealTimeLatency>
<Worst-caseRealTimeLatency>0.121 us</Worst-caseRealTimeLatency>
<PipelineInitiationInterval>3</PipelineInitiationInterval>
<PipelineType>loop auto-rewind (delay=0 clock cycles(s))</PipelineType>
</SummaryOfOverallLatency>
<SummaryOfLoopLatency>
<VITIS_LOOP_157_9>
<Name>VITIS_LOOP_157_9</Name>
<Slack>24.30</Slack>
<TripCount>2</TripCount>
<Latency>2</Latency>
<AbsoluteTimeLatency>60.606 ns</AbsoluteTimeLatency>
<PipelineII>1</PipelineII>
<PipelineDepth>1</PipelineDepth>
<PipelineType>yes</PipelineType>
<InstanceList>
</InstanceList>
</VITIS_LOOP_157_9>
</SummaryOfLoopLatency>
<SummaryOfViolations>
<IssueType>-</IssueType>
<ViolationType>-</ViolationType>
<SourceLocation>../accelerator.cpp:157</SourceLocation>
<SummaryOfLoopViolations>
<VITIS_LOOP_157_9>
<Name>VITIS_LOOP_157_9</Name>
<IssueType>-</IssueType>
<ViolationType>-</ViolationType>
<SourceLocation>../accelerator.cpp:157</SourceLocation>
</VITIS_LOOP_157_9>
</SummaryOfLoopViolations>
</SummaryOfViolations>
</PerformanceEstimates>
<AreaEstimates>
<Resources>
<FF>196</FF>
<AVAIL_FF>141120</AVAIL_FF>
<UTIL_FF>~0</UTIL_FF>
<LUT>352</LUT>
<AVAIL_LUT>70560</AVAIL_LUT>
<UTIL_LUT>~0</UTIL_LUT>
<BRAM_18K>0</BRAM_18K>
<AVAIL_BRAM>432</AVAIL_BRAM>
<UTIL_BRAM>0</UTIL_BRAM>
<DSP>0</DSP>
<AVAIL_DSP>360</AVAIL_DSP>
<UTIL_DSP>0</UTIL_DSP>
<URAM>0</URAM>
<AVAIL_URAM>0</AVAIL_URAM>
<UTIL_URAM>0</UTIL_URAM>
</Resources>
</AreaEstimates>
<InterfaceSummary>
<RtlPorts>
<name>ap_clk</name>
<Object>accelerator_Pipeline_VITIS_LOOP_157_9</Object>
<Type>return value</Type>
<Scope></Scope>
<IOProtocol>ap_ctrl_hs</IOProtocol>
<IOConfig></IOConfig>
<Dir>in</Dir>
<Bits>1</Bits>
<Attribute>control</Attribute>
</RtlPorts>
<RtlPorts>
<name>ap_rst</name>
<Object>accelerator_Pipeline_VITIS_LOOP_157_9</Object>
<Type>return value</Type>
<Scope></Scope>
<IOProtocol>ap_ctrl_hs</IOProtocol>
<IOConfig></IOConfig>
<Dir>in</Dir>
<Bits>1</Bits>
<Attribute>control</Attribute>
</RtlPorts>
<RtlPorts>
<name>ap_start</name>
<Object>accelerator_Pipeline_VITIS_LOOP_157_9</Object>
<Type>return value</Type>
<Scope></Scope>
<IOProtocol>ap_ctrl_hs</IOProtocol>
<IOConfig></IOConfig>
<Dir>in</Dir>
<Bits>1</Bits>
<Attribute>control</Attribute>
</RtlPorts>
<RtlPorts>
<name>ap_done</name>
<Object>accelerator_Pipeline_VITIS_LOOP_157_9</Object>
<Type>return value</Type>
<Scope></Scope>
<IOProtocol>ap_ctrl_hs</IOProtocol>
<IOConfig></IOConfig>
<Dir>out</Dir>
<Bits>1</Bits>
<Attribute>control</Attribute>
</RtlPorts>
<RtlPorts>
<name>ap_idle</name>
<Object>accelerator_Pipeline_VITIS_LOOP_157_9</Object>
<Type>return value</Type>
<Scope></Scope>
<IOProtocol>ap_ctrl_hs</IOProtocol>
<IOConfig></IOConfig>
<Dir>out</Dir>
<Bits>1</Bits>
<Attribute>control</Attribute>
</RtlPorts>
<RtlPorts>
<name>ap_ready</name>
<Object>accelerator_Pipeline_VITIS_LOOP_157_9</Object>
<Type>return value</Type>
<Scope></Scope>
<IOProtocol>ap_ctrl_hs</IOProtocol>
<IOConfig></IOConfig>
<Dir>out</Dir>
<Bits>1</Bits>
<Attribute>control</Attribute>
</RtlPorts>
<RtlPorts>
<name>p_0_0_01214_3_1_lcssa</name>
<Object>p_0_0_01214_3_1_lcssa</Object>
<Type>scalar</Type>
<Scope></Scope>
<IOProtocol>ap_none</IOProtocol>
<IOConfig></IOConfig>
<Dir>in</Dir>
<Bits>16</Bits>
<Attribute>data</Attribute>
</RtlPorts>
<RtlPorts>
<name>p_0_0_01214_3_lcssa</name>
<Object>p_0_0_01214_3_lcssa</Object>
<Type>scalar</Type>
<Scope></Scope>
<IOProtocol>ap_none</IOProtocol>
<IOConfig></IOConfig>
<Dir>in</Dir>
<Bits>16</Bits>
<Attribute>data</Attribute>
</RtlPorts>
<RtlPorts>
<name>p_0_0_01217_3_1_lcssa</name>
<Object>p_0_0_01217_3_1_lcssa</Object>
<Type>scalar</Type>
<Scope></Scope>
<IOProtocol>ap_none</IOProtocol>
<IOConfig></IOConfig>
<Dir>in</Dir>
<Bits>16</Bits>
<Attribute>data</Attribute>
</RtlPorts>
<RtlPorts>
<name>p_0_0_01217_3_lcssa</name>
<Object>p_0_0_01217_3_lcssa</Object>
<Type>scalar</Type>
<Scope></Scope>
<IOProtocol>ap_none</IOProtocol>
<IOConfig></IOConfig>
<Dir>in</Dir>
<Bits>16</Bits>
<Attribute>data</Attribute>
</RtlPorts>
<RtlPorts>
<name>mux_case_1138</name>
<Object>mux_case_1138</Object>
<Type>scalar</Type>
<Scope></Scope>
<IOProtocol>ap_none</IOProtocol>
<IOConfig></IOConfig>
<Dir>in</Dir>
<Bits>16</Bits>
<Attribute>data</Attribute>
</RtlPorts>
<RtlPorts>
<name>mux_case_0137</name>
<Object>mux_case_0137</Object>
<Type>scalar</Type>
<Scope></Scope>
<IOProtocol>ap_none</IOProtocol>
<IOConfig></IOConfig>
<Dir>in</Dir>
<Bits>16</Bits>
<Attribute>data</Attribute>
</RtlPorts>
<RtlPorts>
<name>mux_case_1140</name>
<Object>mux_case_1140</Object>
<Type>scalar</Type>
<Scope></Scope>
<IOProtocol>ap_none</IOProtocol>
<IOConfig></IOConfig>
<Dir>in</Dir>
<Bits>16</Bits>
<Attribute>data</Attribute>
</RtlPorts>
<RtlPorts>
<name>mux_case_0139</name>
<Object>mux_case_0139</Object>
<Type>scalar</Type>
<Scope></Scope>
<IOProtocol>ap_none</IOProtocol>
<IOConfig></IOConfig>
<Dir>in</Dir>
<Bits>16</Bits>
<Attribute>data</Attribute>
</RtlPorts>
<RtlPorts>
<name>mux_case_1142</name>
<Object>mux_case_1142</Object>
<Type>scalar</Type>
<Scope></Scope>
<IOProtocol>ap_none</IOProtocol>
<IOConfig></IOConfig>
<Dir>in</Dir>
<Bits>16</Bits>
<Attribute>data</Attribute>
</RtlPorts>
<RtlPorts>
<name>mux_case_0141</name>
<Object>mux_case_0141</Object>
<Type>scalar</Type>
<Scope></Scope>
<IOProtocol>ap_none</IOProtocol>
<IOConfig></IOConfig>
<Dir>in</Dir>
<Bits>16</Bits>
<Attribute>data</Attribute>
</RtlPorts>
<RtlPorts>
<name>mux_case_1144</name>
<Object>mux_case_1144</Object>
<Type>scalar</Type>
<Scope></Scope>
<IOProtocol>ap_none</IOProtocol>
<IOConfig></IOConfig>
<Dir>in</Dir>
<Bits>16</Bits>
<Attribute>data</Attribute>
</RtlPorts>
<RtlPorts>
<name>mux_case_0143</name>
<Object>mux_case_0143</Object>
<Type>scalar</Type>
<Scope></Scope>
<IOProtocol>ap_none</IOProtocol>
<IOConfig></IOConfig>
<Dir>in</Dir>
<Bits>16</Bits>
<Attribute>data</Attribute>
</RtlPorts>
<RtlPorts>
<name>retval_4_1_0_0_0_load175_out</name>
<Object>retval_4_1_0_0_0_load175_out</Object>
<Type>pointer</Type>
<Scope></Scope>
<IOProtocol>ap_vld</IOProtocol>
<IOConfig></IOConfig>
<Dir>out</Dir>
<Bits>16</Bits>
<Attribute>data</Attribute>
</RtlPorts>
<RtlPorts>
<name>retval_4_1_0_0_0_load175_out_ap_vld</name>
<Object>retval_4_1_0_0_0_load175_out</Object>
<Type>pointer</Type>
<Scope></Scope>
<IOProtocol>ap_vld</IOProtocol>
<IOConfig></IOConfig>
<Dir>out</Dir>
<Bits>1</Bits>
<Attribute>control</Attribute>
</RtlPorts>
<RtlPorts>
<name>retval_4_0_0_0_0_load173_out</name>
<Object>retval_4_0_0_0_0_load173_out</Object>
<Type>pointer</Type>
<Scope></Scope>
<IOProtocol>ap_vld</IOProtocol>
<IOConfig></IOConfig>
<Dir>out</Dir>
<Bits>16</Bits>
<Attribute>data</Attribute>
</RtlPorts>
<RtlPorts>
<name>retval_4_0_0_0_0_load173_out_ap_vld</name>
<Object>retval_4_0_0_0_0_load173_out</Object>
<Type>pointer</Type>
<Scope></Scope>
<IOProtocol>ap_vld</IOProtocol>
<IOConfig></IOConfig>
<Dir>out</Dir>
<Bits>1</Bits>
<Attribute>control</Attribute>
</RtlPorts>
<RtlPorts>
<name>retval_3_1_0_0_0_load171_out</name>
<Object>retval_3_1_0_0_0_load171_out</Object>
<Type>pointer</Type>
<Scope></Scope>
<IOProtocol>ap_vld</IOProtocol>
<IOConfig></IOConfig>
<Dir>out</Dir>
<Bits>16</Bits>
<Attribute>data</Attribute>
</RtlPorts>
<RtlPorts>
<name>retval_3_1_0_0_0_load171_out_ap_vld</name>
<Object>retval_3_1_0_0_0_load171_out</Object>
<Type>pointer</Type>
<Scope></Scope>
<IOProtocol>ap_vld</IOProtocol>
<IOConfig></IOConfig>
<Dir>out</Dir>
<Bits>1</Bits>
<Attribute>control</Attribute>
</RtlPorts>
<RtlPorts>
<name>retval_3_0_0_0_0_load169_out</name>
<Object>retval_3_0_0_0_0_load169_out</Object>
<Type>pointer</Type>
<Scope></Scope>
<IOProtocol>ap_vld</IOProtocol>
<IOConfig></IOConfig>
<Dir>out</Dir>
<Bits>16</Bits>
<Attribute>data</Attribute>
</RtlPorts>
<RtlPorts>
<name>retval_3_0_0_0_0_load169_out_ap_vld</name>
<Object>retval_3_0_0_0_0_load169_out</Object>
<Type>pointer</Type>
<Scope></Scope>
<IOProtocol>ap_vld</IOProtocol>
<IOConfig></IOConfig>
<Dir>out</Dir>
<Bits>1</Bits>
<Attribute>control</Attribute>
</RtlPorts>
<RtlPorts>
<name>retval_2_1_1_0_0_0_load167_out</name>
<Object>retval_2_1_1_0_0_0_load167_out</Object>
<Type>pointer</Type>
<Scope></Scope>
<IOProtocol>ap_vld</IOProtocol>
<IOConfig></IOConfig>
<Dir>out</Dir>
<Bits>16</Bits>
<Attribute>data</Attribute>
</RtlPorts>
<RtlPorts>
<name>retval_2_1_1_0_0_0_load167_out_ap_vld</name>
<Object>retval_2_1_1_0_0_0_load167_out</Object>
<Type>pointer</Type>
<Scope></Scope>
<IOProtocol>ap_vld</IOProtocol>
<IOConfig></IOConfig>
<Dir>out</Dir>
<Bits>1</Bits>
<Attribute>control</Attribute>
</RtlPorts>
<RtlPorts>
<name>retval_2_1_0_0_0_0_load165_out</name>
<Object>retval_2_1_0_0_0_0_load165_out</Object>
<Type>pointer</Type>
<Scope></Scope>
<IOProtocol>ap_vld</IOProtocol>
<IOConfig></IOConfig>
<Dir>out</Dir>
<Bits>16</Bits>
<Attribute>data</Attribute>
</RtlPorts>
<RtlPorts>
<name>retval_2_1_0_0_0_0_load165_out_ap_vld</name>
<Object>retval_2_1_0_0_0_0_load165_out</Object>
<Type>pointer</Type>
<Scope></Scope>
<IOProtocol>ap_vld</IOProtocol>
<IOConfig></IOConfig>
<Dir>out</Dir>
<Bits>1</Bits>
<Attribute>control</Attribute>
</RtlPorts>
<RtlPorts>
<name>retval_2_0_1_0_0_0_load163_out</name>
<Object>retval_2_0_1_0_0_0_load163_out</Object>
<Type>pointer</Type>
<Scope></Scope>
<IOProtocol>ap_vld</IOProtocol>
<IOConfig></IOConfig>
<Dir>out</Dir>
<Bits>16</Bits>
<Attribute>data</Attribute>
</RtlPorts>
<RtlPorts>
<name>retval_2_0_1_0_0_0_load163_out_ap_vld</name>
<Object>retval_2_0_1_0_0_0_load163_out</Object>
<Type>pointer</Type>
<Scope></Scope>
<IOProtocol>ap_vld</IOProtocol>
<IOConfig></IOConfig>
<Dir>out</Dir>
<Bits>1</Bits>
<Attribute>control</Attribute>
</RtlPorts>
<RtlPorts>
<name>retval_2_0_0_0_0_0_load161_out</name>
<Object>retval_2_0_0_0_0_0_load161_out</Object>
<Type>pointer</Type>
<Scope></Scope>
<IOProtocol>ap_vld</IOProtocol>
<IOConfig></IOConfig>
<Dir>out</Dir>
<Bits>16</Bits>
<Attribute>data</Attribute>
</RtlPorts>
<RtlPorts>
<name>retval_2_0_0_0_0_0_load161_out_ap_vld</name>
<Object>retval_2_0_0_0_0_0_load161_out</Object>
<Type>pointer</Type>
<Scope></Scope>
<IOProtocol>ap_vld</IOProtocol>
<IOConfig></IOConfig>
<Dir>out</Dir>
<Bits>1</Bits>
<Attribute>control</Attribute>
</RtlPorts>
<RtlPorts>
<name>retval_1_1_1_0_0_0_load159_out</name>
<Object>retval_1_1_1_0_0_0_load159_out</Object>
<Type>pointer</Type>
<Scope></Scope>
<IOProtocol>ap_vld</IOProtocol>
<IOConfig></IOConfig>
<Dir>out</Dir>
<Bits>16</Bits>
<Attribute>data</Attribute>
</RtlPorts>
<RtlPorts>
<name>retval_1_1_1_0_0_0_load159_out_ap_vld</name>
<Object>retval_1_1_1_0_0_0_load159_out</Object>
<Type>pointer</Type>
<Scope></Scope>
<IOProtocol>ap_vld</IOProtocol>
<IOConfig></IOConfig>
<Dir>out</Dir>
<Bits>1</Bits>
<Attribute>control</Attribute>
</RtlPorts>
<RtlPorts>
<name>retval_1_1_0_0_0_0_load157_out</name>
<Object>retval_1_1_0_0_0_0_load157_out</Object>
<Type>pointer</Type>
<Scope></Scope>
<IOProtocol>ap_vld</IOProtocol>
<IOConfig></IOConfig>
<Dir>out</Dir>
<Bits>16</Bits>
<Attribute>data</Attribute>
</RtlPorts>
<RtlPorts>
<name>retval_1_1_0_0_0_0_load157_out_ap_vld</name>
<Object>retval_1_1_0_0_0_0_load157_out</Object>
<Type>pointer</Type>
<Scope></Scope>
<IOProtocol>ap_vld</IOProtocol>
<IOConfig></IOConfig>
<Dir>out</Dir>
<Bits>1</Bits>
<Attribute>control</Attribute>
</RtlPorts>
<RtlPorts>
<name>retval_1_0_1_0_0_0_load155_out</name>
<Object>retval_1_0_1_0_0_0_load155_out</Object>
<Type>pointer</Type>
<Scope></Scope>
<IOProtocol>ap_vld</IOProtocol>
<IOConfig></IOConfig>
<Dir>out</Dir>
<Bits>16</Bits>
<Attribute>data</Attribute>
</RtlPorts>
<RtlPorts>
<name>retval_1_0_1_0_0_0_load155_out_ap_vld</name>
<Object>retval_1_0_1_0_0_0_load155_out</Object>
<Type>pointer</Type>
<Scope></Scope>
<IOProtocol>ap_vld</IOProtocol>
<IOConfig></IOConfig>
<Dir>out</Dir>
<Bits>1</Bits>
<Attribute>control</Attribute>
</RtlPorts>
<RtlPorts>
<name>retval_1_0_0_0_0_0_load153_out</name>
<Object>retval_1_0_0_0_0_0_load153_out</Object>
<Type>pointer</Type>
<Scope></Scope>
<IOProtocol>ap_vld</IOProtocol>
<IOConfig></IOConfig>
<Dir>out</Dir>
<Bits>16</Bits>
<Attribute>data</Attribute>
</RtlPorts>
<RtlPorts>
<name>retval_1_0_0_0_0_0_load153_out_ap_vld</name>
<Object>retval_1_0_0_0_0_0_load153_out</Object>
<Type>pointer</Type>
<Scope></Scope>
<IOProtocol>ap_vld</IOProtocol>
<IOConfig></IOConfig>
<Dir>out</Dir>
<Bits>1</Bits>
<Attribute>control</Attribute>
</RtlPorts>
</InterfaceSummary>
</Module>
<Module>
<Name>accelerator</Name>
<PerformanceEstimates>
<SummaryOfTimingAnalysis>
<TargetClockPeriod>30.30</TargetClockPeriod>
<ClockUncertainty>6.00</ClockUncertainty>
<EstimatedClockPeriod>20.707</EstimatedClockPeriod>
</SummaryOfTimingAnalysis>
<SummaryOfOverallLatency>
<Best-caseLatency>97</Best-caseLatency>
<Average-caseLatency>20598</Average-caseLatency>
<Worst-caseLatency>41098</Worst-caseLatency>
<Best-caseRealTimeLatency>2.939 us</Best-caseRealTimeLatency>
<Average-caseRealTimeLatency>0.624 ms</Average-caseRealTimeLatency>
<Worst-caseRealTimeLatency>1.245 ms</Worst-caseRealTimeLatency>
<PipelineInitiationInterval>98 ~ 41099</PipelineInitiationInterval>
<PipelineType>no</PipelineType>
</SummaryOfOverallLatency>
<SummaryOfViolations>
<IssueType>-</IssueType>
<ViolationType>-</ViolationType>
<SourceLocation>../accelerator.cpp:7</SourceLocation>
</SummaryOfViolations>
</PerformanceEstimates>
<AreaEstimates>
<Resources>
<DSP>18</DSP>
<AVAIL_DSP>360</AVAIL_DSP>
<UTIL_DSP>5</UTIL_DSP>
<FF>3485</FF>
<AVAIL_FF>141120</AVAIL_FF>
<UTIL_FF>2</UTIL_FF>
<LUT>7107</LUT>
<AVAIL_LUT>70560</AVAIL_LUT>
<UTIL_LUT>10</UTIL_LUT>
<BRAM_18K>0</BRAM_18K>
<AVAIL_BRAM>432</AVAIL_BRAM>
<UTIL_BRAM>0</UTIL_BRAM>
<URAM>0</URAM>
<AVAIL_URAM>0</AVAIL_URAM>
<UTIL_URAM>0</UTIL_URAM>
</Resources>
</AreaEstimates>
<InterfaceSummary>
<RtlPorts>
<name>ap_clk</name>
<Object>accelerator</Object>
<Type>return value</Type>
<Scope></Scope>
<IOProtocol>ap_ctrl_hs</IOProtocol>
<IOConfig></IOConfig>
<Dir>in</Dir>
<Bits>1</Bits>
<Attribute>control</Attribute>
</RtlPorts>
<RtlPorts>
<name>ap_rst</name>
<Object>accelerator</Object>
<Type>return value</Type>
<Scope></Scope>
<IOProtocol>ap_ctrl_hs</IOProtocol>
<IOConfig></IOConfig>
<Dir>in</Dir>
<Bits>1</Bits>
<Attribute>control</Attribute>
</RtlPorts>
<RtlPorts>
<name>ap_start</name>
<Object>accelerator</Object>
<Type>return value</Type>
<Scope></Scope>
<IOProtocol>ap_ctrl_hs</IOProtocol>
<IOConfig></IOConfig>
<Dir>in</Dir>
<Bits>1</Bits>
<Attribute>control</Attribute>
</RtlPorts>
<RtlPorts>
<name>ap_done</name>
<Object>accelerator</Object>
<Type>return value</Type>
<Scope></Scope>
<IOProtocol>ap_ctrl_hs</IOProtocol>
<IOConfig></IOConfig>
<Dir>out</Dir>
<Bits>1</Bits>
<Attribute>control</Attribute>
</RtlPorts>
<RtlPorts>
<name>ap_idle</name>
<Object>accelerator</Object>
<Type>return value</Type>
<Scope></Scope>
<IOProtocol>ap_ctrl_hs</IOProtocol>
<IOConfig></IOConfig>
<Dir>out</Dir>
<Bits>1</Bits>
<Attribute>control</Attribute>
</RtlPorts>
<RtlPorts>
<name>ap_ready</name>
<Object>accelerator</Object>
<Type>return value</Type>
<Scope></Scope>
<IOProtocol>ap_ctrl_hs</IOProtocol>
<IOConfig></IOConfig>
<Dir>out</Dir>
<Bits>1</Bits>
<Attribute>control</Attribute>
</RtlPorts>
<RtlPorts>
<name>ap_return</name>
<Object>accelerator</Object>
<Type>return value</Type>
<Scope></Scope>
<IOProtocol>ap_ctrl_hs</IOProtocol>
<IOConfig></IOConfig>
<Dir>out</Dir>
<Bits>256</Bits>
<Attribute>data</Attribute>
</RtlPorts>
<RtlPorts>
<name>w1_address0</name>
<Object>w1</Object>
<Type>array</Type>
<Scope></Scope>
<IOProtocol>ap_memory</IOProtocol>
<IOConfig></IOConfig>
<Dir>out</Dir>
<Bits>2</Bits>
<Attribute>address</Attribute>
<CType>int</CType>
</RtlPorts>
<RtlPorts>
<name>w1_ce0</name>
<Object>w1</Object>
<Type>array</Type>
<Scope></Scope>
<IOProtocol>ap_memory</IOProtocol>
<IOConfig></IOConfig>
<Dir>out</Dir>
<Bits>1</Bits>
<Attribute>control</Attribute>
<CType>int</CType>
</RtlPorts>
<RtlPorts>
<name>w1_q0</name>
<Object>w1</Object>
<Type>array</Type>
<Scope></Scope>
<IOProtocol>ap_memory</IOProtocol>
<IOConfig></IOConfig>
<Dir>in</Dir>
<Bits>16</Bits>
<Attribute>data</Attribute>
<CType>int</CType>
</RtlPorts>
<RtlPorts>
<name>w1_address1</name>
<Object>w1</Object>
<Type>array</Type>
<Scope></Scope>
<IOProtocol>ap_memory</IOProtocol>
<IOConfig></IOConfig>
<Dir>out</Dir>
<Bits>2</Bits>
<Attribute>address</Attribute>
<CType>int</CType>
</RtlPorts>
<RtlPorts>
<name>w1_ce1</name>
<Object>w1</Object>
<Type>array</Type>
<Scope></Scope>
<IOProtocol>ap_memory</IOProtocol>
<IOConfig></IOConfig>
<Dir>out</Dir>
<Bits>1</Bits>
<Attribute>control</Attribute>
<CType>int</CType>
</RtlPorts>
<RtlPorts>
<name>w1_q1</name>
<Object>w1</Object>
<Type>array</Type>
<Scope></Scope>
<IOProtocol>ap_memory</IOProtocol>
<IOConfig></IOConfig>
<Dir>in</Dir>
<Bits>16</Bits>
<Attribute>data</Attribute>
<CType>int</CType>
</RtlPorts>
<RtlPorts>
<name>w2_address0</name>
<Object>w2</Object>
<Type>array</Type>
<Scope></Scope>
<IOProtocol>ap_memory</IOProtocol>
<IOConfig></IOConfig>
<Dir>out</Dir>
<Bits>2</Bits>
<Attribute>address</Attribute>
<CType>int</CType>
</RtlPorts>
<RtlPorts>
<name>w2_ce0</name>
<Object>w2</Object>
<Type>array</Type>
<Scope></Scope>
<IOProtocol>ap_memory</IOProtocol>
<IOConfig></IOConfig>
<Dir>out</Dir>
<Bits>1</Bits>
<Attribute>control</Attribute>
<CType>int</CType>
</RtlPorts>
<RtlPorts>
<name>w2_q0</name>
<Object>w2</Object>
<Type>array</Type>
<Scope></Scope>
<IOProtocol>ap_memory</IOProtocol>
<IOConfig></IOConfig>
<Dir>in</Dir>
<Bits>16</Bits>
<Attribute>data</Attribute>
<CType>int</CType>
</RtlPorts>
<RtlPorts>
<name>w2_address1</name>
<Object>w2</Object>
<Type>array</Type>
<Scope></Scope>
<IOProtocol>ap_memory</IOProtocol>
<IOConfig></IOConfig>
<Dir>out</Dir>
<Bits>2</Bits>
<Attribute>address</Attribute>
<CType>int</CType>
</RtlPorts>
<RtlPorts>
<name>w2_ce1</name>
<Object>w2</Object>
<Type>array</Type>
<Scope></Scope>
<IOProtocol>ap_memory</IOProtocol>
<IOConfig></IOConfig>
<Dir>out</Dir>
<Bits>1</Bits>
<Attribute>control</Attribute>
<CType>int</CType>
</RtlPorts>
<RtlPorts>
<name>w2_q1</name>
<Object>w2</Object>
<Type>array</Type>
<Scope></Scope>
<IOProtocol>ap_memory</IOProtocol>
<IOConfig></IOConfig>
<Dir>in</Dir>
<Bits>16</Bits>
<Attribute>data</Attribute>
<CType>int</CType>
</RtlPorts>
<RtlPorts>
<name>bias_1_address0</name>
<Object>bias_1</Object>
<Type>array</Type>
<Scope></Scope>
<IOProtocol>ap_memory</IOProtocol>
<IOConfig></IOConfig>
<Dir>out</Dir>
<Bits>1</Bits>
<Attribute>address</Attribute>
<CType>int</CType>
</RtlPorts>
<RtlPorts>
<name>bias_1_ce0</name>
<Object>bias_1</Object>
<Type>array</Type>
<Scope></Scope>
<IOProtocol>ap_memory</IOProtocol>
<IOConfig></IOConfig>
<Dir>out</Dir>
<Bits>1</Bits>
<Attribute>control</Attribute>
<CType>int</CType>
</RtlPorts>
<RtlPorts>
<name>bias_1_q0</name>
<Object>bias_1</Object>
<Type>array</Type>
<Scope></Scope>
<IOProtocol>ap_memory</IOProtocol>
<IOConfig></IOConfig>
<Dir>in</Dir>
<Bits>16</Bits>
<Attribute>data</Attribute>
<CType>int</CType>
</RtlPorts>
<RtlPorts>
<name>bias_2_address0</name>
<Object>bias_2</Object>
<Type>array</Type>
<Scope></Scope>
<IOProtocol>ap_memory</IOProtocol>
<IOConfig></IOConfig>
<Dir>out</Dir>
<Bits>1</Bits>
<Attribute>address</Attribute>
<CType>int</CType>
</RtlPorts>
<RtlPorts>
<name>bias_2_ce0</name>
<Object>bias_2</Object>
<Type>array</Type>
<Scope></Scope>
<IOProtocol>ap_memory</IOProtocol>
<IOConfig></IOConfig>
<Dir>out</Dir>
<Bits>1</Bits>
<Attribute>control</Attribute>
<CType>int</CType>
</RtlPorts>
<RtlPorts>
<name>bias_2_q0</name>
<Object>bias_2</Object>
<Type>array</Type>
<Scope></Scope>
<IOProtocol>ap_memory</IOProtocol>
<IOConfig></IOConfig>
<Dir>in</Dir>
<Bits>16</Bits>
<Attribute>data</Attribute>
<CType>int</CType>
</RtlPorts>
<RtlPorts>
<name>training</name>
<Object>training</Object>
<Type>scalar</Type>
<Scope></Scope>
<IOProtocol>ap_none</IOProtocol>
<IOConfig></IOConfig>
<Dir>in</Dir>
<Bits>16</Bits>
<Attribute>data</Attribute>
<CType>int</CType>
</RtlPorts>
</InterfaceSummary>
</Module>
</ModuleInformation>

<FIFOInformation>
</FIFOInformation>

</profile>
